[
    {
        "ID": 1001,
        "Name": "攻擊力加成",
        "Type": 0,
        "BuffType": "ATK",
        "Value": 2,
        "Probability": 0.2
    },
    {
        "ID": 1002,
        "Name": "防禦力加成",
        "Type": 0,
        "BuffType": "DEF",
        "Value": 2,
        "Probability": 0.2
    },
    {
        "ID": 1003,
        "Name": "血量加成",
        "Type": 0,
        "BuffType": "HP",
        "Value": 2,
        "Probability": 0.12
    },
    {
        "ID": 1004,
        "Name": "血量減少",
        "Type": 1,
        "BuffType": "HP",
        "Value": 0.5,
        "Probability": 0.18
    },
    {
        "ID": 1005,
        "Name": "金幣減半",
        "Type": 1,
        "BuffType": "COIN",
        "Value": 0.5,
        "Probability": 0.18
    },
    {
        "ID": 1006,
        "Name": "敵人血量雙倍",
        "Type": 1,
        "BuffType": "BOSS_HP",
        "Value": 2,
        "Probability": 0.12
    }
]